<annotation>
	<folder>newimages</folder>
	<filename>108.jpg</filename>
	<path>D:\PycharmProjects\2024A\标注\newimages\108.jpg</path>
	<source>
		<database>Unknown</database>
	</source>
	<size>
		<width>640</width>
		<height>855</height>
		<depth>3</depth>
	</size>
	<segmented>0</segmented>
	<object>
		<name>loopy</name>
		<pose>Unspecified</pose>
		<truncated>0</truncated>
		<difficult>0</difficult>
		<bndbox>
			<xmin>204</xmin>
			<ymin>14</ymin>
			<xmax>466</xmax>
			<ymax>261</ymax>
		</bndbox>
	</object>
	<object>
		<name>loopy</name>
		<pose>Unspecified</pose>
		<truncated>0</truncated>
		<difficult>0</difficult>
		<bndbox>
			<xmin>222</xmin>
			<ymin>499</ymin>
			<xmax>494</xmax>
			<ymax>773</ymax>
		</bndbox>
	</object>
</annotation>
